cuhk_seis/__init__.py
cuhk_seis/basic_utils.py
cuhk_seis/dt_cc_py.py
cuhk_seis/eve_wf.py
cuhk_seis/fft_analysis.py
cuhk_seis/mp_day_split.py
cuhk_seis/phase_convert.py
cuhk_seis/reloc_related.py
cuhk_seis/scc.py
cuhk_seis-0.0.2.dist-info/LICENSE
cuhk_seis-0.0.2.dist-info/METADATA
cuhk_seis-0.0.2.dist-info/WHEEL
cuhk_seis-0.0.2.dist-info/top_level.txt
cuhk_seis-0.0.2.dist-info/RECORD
