Metadata-Version: 2.1
Name: cuhk-seis
Version: 0.0.2
Summary: package for earthquake location purpose
Home-page: UNKNOWN
Author: Hardy ZI
Author-email: zijinping@hotmail.com
License: MIT
Platform: UNKNOWN
Requires-Python: >=3.7
License-File: LICENSE
Requires-Dist: EQTransformer (>=0.1.59)
Requires-Dist: obspy
Requires-Dist: tqdm (==4.48.0)
Requires-Dist: jupyter
Requires-Dist: scipy (==1.4.1)
Requires-Dist: numpy (>=1.21.0)
